hpo4dl/__init__.py
hpo4dl/configuration_manager/__init__.py
hpo4dl/configuration_manager/abstract_configuration_manager.py
hpo4dl/configuration_manager/configuration_manager.py
hpo4dl/graybox_wrapper/__init__.py
hpo4dl/graybox_wrapper/abstract_graybox_wrapper.py
hpo4dl/graybox_wrapper/graybox_wrapper.py
hpo4dl/optimizers/__init__.py
hpo4dl/optimizers/abstract_optimizer.py
hpo4dl/optimizers/dyhpo/__init__.py
hpo4dl/optimizers/dyhpo/data_loader/__init__.py
hpo4dl/optimizers/dyhpo/data_loader/tabular_data_loader.py
hpo4dl/optimizers/dyhpo/dataset/__init__.py
hpo4dl/optimizers/dyhpo/dataset/tabular_dataset.py
hpo4dl/optimizers/dyhpo/dyhpo_optimizer.py
hpo4dl/optimizers/dyhpo/surrogate_models/dyhpo.py
hpo4dl/optimizers/hyperband/__init__.py
hpo4dl/optimizers/hyperband/hyperband.py
hpo4dl/test/test_configuration_manager.py
hpo4dl/test/test_hyperband.py
hpo4dl/tuner.py
hpo4dl/utils/__init__.py
hpo4dl/utils/configuration_dataclasses.py
hpo4dl/utils/result_logger.py
hpo4dl-0.1.0.dist-info/METADATA
hpo4dl-0.1.0.dist-info/WHEEL
hpo4dl-0.1.0.dist-info/RECORD
