Metadata-Version: 2.1
Name: hpo4dl
Version: 0.1.0
Summary: Hyper parameter optimization for deep learning
Home-page: https://github.com/releaunifreiburg/HPO4DL
License: MIT
Keywords: Hyperparameter Optimization,AutoML
Author: Rishan Senanayake
Author-email: rd.senanayake@gmail.com
Maintainer: Sebastian Pineda
Maintainer-email: pineda@cs.uni-freiburg.de
Requires-Python: >=3.8,<4.0
Classifier: Intended Audience :: Developers
Classifier: Intended Audience :: Science/Research
Classifier: License :: OSI Approved :: MIT License
Classifier: Natural Language :: English
Classifier: Operating System :: MacOS
Classifier: Operating System :: Microsoft :: Windows
Classifier: Operating System :: POSIX :: Linux
Classifier: Programming Language :: Python :: 3
Classifier: Programming Language :: Python :: 3.8
Classifier: Programming Language :: Python :: 3.9
Classifier: Programming Language :: Python :: 3.10
Classifier: Programming Language :: Python :: 3.11
Classifier: Topic :: Scientific/Engineering :: Artificial Intelligence
Requires-Dist: configspace (>=0.7.1,<0.8.0)
Requires-Dist: gpytorch (>=1.11,<2.0)
Requires-Dist: pandas (>=2.0.3,<3.0.0)
Requires-Dist: scikit-learn (>=1.3.0,<2.0.0)
Requires-Dist: timm (>=0.9.2,<0.10.0)
Project-URL: Repository, https://github.com/releaunifreiburg/HPO4DL
